ofjustpy_engine/HCType.py
ofjustpy_engine/HC_Div_type_mixins.py
ofjustpy_engine/HC_type_mixins_extn.py
ofjustpy_engine/SHC_types_mixin.py
ofjustpy_engine/TF_impl.py
ofjustpy_engine/WebPage_type_mixin.py
ofjustpy_engine/__init__.py
ofjustpy_engine/justpy.py
ofjustpy_engine/mutable_Div_TF.py
ofjustpy_engine/mutable_HC_TF.py
ofjustpy_engine/mutable_TF_impl.py
ofjustpy_engine/static_core_tracker.py
ofjustpy_engine/tailwind_svelte_component_mixins.py
ofjustpy_engine/tracker.py
ofjustpy_engine/jpcore/AppDB.py
ofjustpy_engine/jpcore/jpconfig.py
ofjustpy_engine/jpcore/justpy_app.py
ofjustpy_engine/jpcore/justpy_config.py
ofjustpy_engine/jpcore/template.py
ofjustpy_engine/jpcore/utilities.py
ofjustpy_engine/templates/__init__.py
ofjustpy_engine/templates/favicon.html
ofjustpy_engine/templates/main.html
ofjustpy_engine/templates/optional_packages.html
ofjustpy_engine/templates/production_hosting.html
ofjustpy_engine/templates/quasar.html
ofjustpy_engine/templates/svelte.html
ofjustpy_engine/templates/tailwind.html
ofjustpy_engine/templates/tailwindui.html
ofjustpy_engine/templates/css/form.css
ofjustpy_engine/templates/css/pygments.css
ofjustpy_engine/templates/js/comm_channel.js
ofjustpy_engine/templates/js/event_handler.js
ofjustpy_engine/templates/js/event_handler_ssr.js
ofjustpy_engine/templates/js/jsonpatch.js
ofjustpy_engine/templates/js/justpy_core.js
ofjustpy_engine/templates/js/svelte/bundle.iife.js
ofjustpy_engine/templates/js/svelte/bundle.iife.js.map
ofjustpy_engine/templates/js/svelte/component_generator.js
ofjustpy_engine/templates/js/svelte/style.css
ofjustpy_engine/templates/local/ag-grid-community.js
ofjustpy_engine/templates/local/ag-grid-enterprise.js
ofjustpy_engine/templates/local/animate.css
ofjustpy_engine/templates/local/jquery.js
ofjustpy_engine/templates/local/quasar.css
ofjustpy_engine/templates/local/tailwind.css
ofjustpy_engine/templates/local/tailwindui.css
ofjustpy_engine/templates/local/vue.js
ofjustpy_engine-1.1.3.dist-info/LICENSE
ofjustpy_engine-1.1.3.dist-info/WHEEL
ofjustpy_engine-1.1.3.dist-info/METADATA
ofjustpy_engine-1.1.3.dist-info/RECORD
